{
    "wallpaper": "/home/morgaux/var/Pictures/Wallpapers/stone.jpg",
    "alpha": "100",
    "special": {
        "background": "#090504",
        "foreground": "#e9e7e4",
        "cursor": "#e9e7e4"
    },
    "colors": {
        "color0": "#090504",
        "color1": "#9D8C71",
        "color2": "#B0AAA2",
        "color3": "#C5BAAB",
        "color4": "#CFC6B7",
        "color5": "#BEC2C1",
        "color6": "#D2D0CD",
        "color7": "#e9e7e4",
        "color8": "#a3a19f",
        "color9": "#9D8C71",
        "color10": "#B0AAA2",
        "color11": "#C5BAAB",
        "color12": "#CFC6B7",
        "color13": "#BEC2C1",
        "color14": "#D2D0CD",
        "color15": "#e9e7e4"
    }
}